pytest_markdown_report/__init__.py
pytest_markdown_report/plugin.py
pytest_markdown_report/py.typed
pytest_markdown_report-0.1.1.dist-info/METADATA
pytest_markdown_report-0.1.1.dist-info/WHEEL
pytest_markdown_report-0.1.1.dist-info/entry_points.txt
pytest_markdown_report-0.1.1.dist-info/licenses/LICENSE
pytest_markdown_report-0.1.1.dist-info/RECORD
