Metadata-Version: 2.4
Name: pytest-markdown-report
Version: 0.1.1
Summary: Token-efficient markdown test reports for LLM-based TDD agents
Project-URL: Homepage, https://github.com/ddaanet/pytest-markdown-report
Project-URL: Repository, https://github.com/ddaanet/pytest-markdown-report
Author-email: David Allouche <david@ddaa.net>
License-Expression: MIT
License-File: LICENSE
Classifier: Framework :: Pytest
Classifier: License :: OSI Approved :: MIT License
Classifier: Programming Language :: Python :: 3
Classifier: Programming Language :: Python :: 3.11
Classifier: Programming Language :: Python :: 3.12
Classifier: Programming Language :: Python :: 3.13
Classifier: Programming Language :: Python :: 3.14
Requires-Python: >=3.11
Requires-Dist: pytest>=7.0
